django_app_manager/__init__.py
django_app_manager/apps.py
django_app_manager/conf/app_template/__init__.py-tpl
django_app_manager/conf/app_template/admin.py-tpl
django_app_manager/conf/app_template/apps.py-tpl
django_app_manager/conf/app_template/migrations/__init__.py-tpl
django_app_manager/conf/app_template/models.py-tpl
django_app_manager/conf/app_template/tests.py-tpl
django_app_manager/conf/app_template/urls.py-tpl
django_app_manager/conf/app_template/views.py-tpl
django_app_manager/management/__init__.py
django_app_manager/management/commands/__init__.py
django_app_manager/management/commands/startapp.py
django_app_manager-0.1.8.data/data/app_template/__init__.py-tpl
django_app_manager-0.1.8.data/data/app_template/admin.py-tpl
django_app_manager-0.1.8.data/data/app_template/apps.py-tpl
django_app_manager-0.1.8.data/data/app_template/migrations/__init__.py-tpl
django_app_manager-0.1.8.data/data/app_template/models.py-tpl
django_app_manager-0.1.8.data/data/app_template/tests.py-tpl
django_app_manager-0.1.8.data/data/app_template/urls.py-tpl
django_app_manager-0.1.8.data/data/app_template/views.py-tpl
django_app_manager-0.1.8.dist-info/WHEEL
django_app_manager-0.1.8.dist-info/METADATA
django_app_manager-0.1.8.dist-info/RECORD
