Metadata-Version: 2.3
Name: django-app-manager
Version: 0.1.8
Summary: Add your description here
Requires-Dist: django>=4.2.26
Requires-Dist: libcst>=1.8.6
Requires-Python: >=3.10
